{
    "patches": [
        {
            "label": "2025-11-25_15-29-00",
            "content": "@@ -205,83 +205,8 @@\n lse%0A\n-        if self.number is not int or %22()%22 or %22.%22:%0A            return False%0A\n     \n",
            "lines": "83"
        },
        {
            "label": "2025-11-25_17-56-14",
            "content": "@@ -193,32 +193,107 @@\n    return False%0A\n+        if self.number is not int or %22()%22 or %22.%22:%0A            return False%0A\n         return T\n",
            "lines": "85"
        },
        {
            "label": "2025-11-25_17-56-45",
            "content": "@@ -205,71 +205,8 @@\n lse%0A\n-        if not self.number.isdigit():%0A            return False%0A\n     \n",
            "lines": "83"
        },
        {
            "label": "2025-11-25_17-59-34",
            "content": "@@ -695,20 +695,16 @@\n      if \n-not \n fone.isV\n@@ -719,65 +719,8 @@\n     \n-        print(%22fail: invalid number%22)%0A            return%0A\n     \n@@ -745,25 +745,16 @@\n nd(fone)\n-%0A        \n %0A%0A    de\n",
            "lines": "85"
        },
        {
            "label": "2025-11-25_18-02-07",
            "content": "@@ -216,32 +216,11 @@\n  if \n-any(c.isalpha() for c in\n+not\n  sel\n@@ -227,16 +227,25 @@\n f.number\n+.isdigit(\n ):%0A     \n",
            "lines": "88"
        },
        {
            "label": "2025-11-25_18-09-31",
            "content": "@@ -2127,73 +2127,8 @@\n ex)%0A\n-        elif args%5B0%5D == %22tfav%22:%0A            contatos.toggleFav()%0A\n main\n",
            "lines": "88"
        },
        {
            "label": "2025-11-25_18-10-15",
            "content": "@@ -528,26 +528,8 @@\n  str\n-, fone: list%5BFone%5D\n ):%0A \n@@ -548,14 +548,25 @@\n fone\n-= fone\n+: list%5BFone%5D = %5B%5D\n %0A   \n",
            "lines": "90"
        },
        {
            "label": "2025-11-26_13-09-17",
            "content": "@@ -1603,11 +1603,8 @@\n t(%22%22\n- %5B%5D\n )%0A  \n",
            "lines": "90"
        },
        {
            "label": "2025-11-26_13-09-40",
            "content": "@@ -1,2207 +1,61 @@\n-class Fone:%0A    def __init__(self, id: str, number: str):%0A        self.id = id%0A        self.number = number%0A%0A    def isValid(self) -%3E bool:%0A        if not self.id or not self.number:%0A            return False%0A        if any(c.isalpha() for c in self.number):%0A            return False%0A        return True%0A    %0A    def getId(self):%0A        return self.id%0A    %0A    def getNumber(self):%0A        return self.number%0A    %0A    def __str__(self):%0A        return f%22%7Bself.id%7D:%7Bself.number%7D%22%0A    %0Aclass Contact:%0A    def __init__(self, name: str, fone: list%5BFone%5D):%0A        self.fone= fone%0A        self.name = name%0A        self.fav: bool = False%0A%0A    def addFone(self, id: str, number: str):%0A        fone = Fone(id, number)%0A        if not fone.isValid():%0A            print(%22fail: invalid number%22)%0A            return%0A        self.fone.append(fone)%0A        %0A%0A    def rmFone(self, index: int):%0A        self.fone.pop(index)%0A%0A    def toggleFav(self):%0A        if self.fav == False:%0A            self.fav = True%0A            return%0A        else:%0A            self.fav = False%0A%0A    def isFav(self) -%3E bool:%0A        if self.fav == True:%0A            return True%0A        else:%0A            return False%0A        %0A    def getFones(self):%0A        return self.fone%0A    %0A    def getName(self):%0A        return self.name%0A    %0A    def setName(self, name: str):%0A        self.name = name%0A%0A    def __str__(self):%0A        fone = %22, %22.join(%5Bstr(x) for x in self.fone%5D)%0A        if self.fav == True:%0A            return f%22@ %7Bself.name%7D %5B%7Bfone%7D%5D%22%0A        else:%0A            return f%22- %7Bself.name%7D %5B%7Bfone%7D%5D%22%0A        %0Adef main():%0A    contatos = Contact()%0A    while True:%0A        line = input()%0A        print(%22$%22 + line)%0A        args: list%5Bstr%5D = line.split()%0A        if args%5B0%5D == %22end%22:%0A            break%0A        elif args%5B0%5D == %22show%22:%0A            print(contatos)%0A        elif args%5B0%5D == %22init%22:%0A            name = args%5B1%5D%0A            contatos.setName(name)%0A        elif args%5B0%5D == %22add%22:%0A            id = args%5B1%5D%0A            number = args%5B2%5D%0A            contatos.addFone(id, number)%0A        elif args%5B0%5D == %22rm%22:%0A            index = int(args%5B1%5D)%0A            contatos.rmFone(index)%0A        elif args%5B0%5D == %22tfav%22:%0A            contatos.toggleFav()%0Amain()\n+@@ -1597,16 +1597,21 @@%0A Contact(%0A+%2522%2522 %255B%255D%0A )%250A    wh\n %0A\n",
            "lines": "4"
        },
        {
            "label": "2025-11-26_13-09-40",
            "content": "@@ -1601,13 +1601,8 @@\n act(\n-%22%22 %5B%5D\n )%0A  \n",
            "lines": "90"
        },
        {
            "label": "2025-11-26_13-09-58",
            "content": "@@ -546,13 +546,8 @@\n one%5D\n- = %5B%5D\n ):%0A \n@@ -1599,16 +1599,19 @@\n ntact(%22%22\n+ %5B%5D\n )%0A    wh\n",
            "lines": "90"
        },
        {
            "label": "2025-11-26_13-10-27",
            "content": "@@ -567,17 +567,16 @@\n elf.fone\n- \n = fone%0A \n",
            "lines": "90"
        },
        {
            "label": "2025-11-26_13-34-12",
            "content": "class Fone:\n    def __init__(self, id: str, number: str):\n        self.id = id\n        self.number = number\n\n    def isValid(self) -> bool:\n        if not self.id or not self.number:\n            return False\n        if any(c.isalpha() for c in self.number):\n            return False\n        return True\n    \n    def getId(self):\n        return self.id\n    \n    def getNumber(self):\n        return self.number\n    \n    def __str__(self):\n        return f\"{self.id}:{self.number}\"\n    \nclass Contact:\n    def __init__(self, name: str, fone: list[Fone] = []):\n        self.fone = fone\n        self.name = name\n        self.fav: bool = False\n\n    def addFone(self, id: str, number: str):\n        fone = Fone(id, number)\n        if not fone.isValid():\n            print(\"fail: invalid number\")\n            return\n        self.fone.append(fone)\n        \n\n    def rmFone(self, index: int):\n        self.fone.pop(index)\n\n    def toggleFav(self):\n        if self.fav == False:\n            self.fav = True\n            return\n        else:\n            self.fav = False\n\n    def isFav(self) -> bool:\n        if self.fav == True:\n            return True\n        else:\n            return False\n        \n    def getFones(self):\n        return self.fone\n    \n    def getName(self):\n        return self.name\n    \n    def setName(self, name: str):\n        self.name = name\n\n    def __str__(self):\n        fone = \", \".join([str(x) for x in self.fone])\n        if self.fav == True:\n            return f\"@ {self.name} [{fone}]\"\n        else:\n            return f\"- {self.name} [{fone}]\"\n        \ndef main():\n    contatos = Contact(\"\")\n    while True:\n        line = input()\n        print(\"$\" + line)\n        args: list[str] = line.split()\n        if args[0] == \"end\":\n            break\n        elif args[0] == \"show\":\n            print(contatos)\n        elif args[0] == \"init\":\n            name = args[1]\n            contatos.setName(name)\n        elif args[0] == \"add\":\n            id = args[1]\n            number = args[2]\n            contatos.addFone(id, number)\n        elif args[0] == \"rm\":\n            index = int(args[1])\n            contatos.rmFone(index)\n        elif args[0] == \"tfav\":\n            contatos.toggleFav()\nmain()\n",
            "lines": "90"
        }
    ]
}